{"cameraMode":{"drawMode":0,"name":"Shaded","section":"Shading Mode"},"sceneLighting":true,"audioPlay":false,"sceneViewState":{"m_AlwaysRefresh":false,"showFog":true,"showSkybox":true,"showFlares":true,"showImageEffects":true,"showParticleSystems":true,"showVisualEffectGraphs":true,"m_FxEnabled":true},"in2DMode":false,"pivot":{"x":-17.508031845092775,"y":-0.06128811091184616,"z":-22.285789489746095},"rotation":{"x":0.34838518500328066,"y":-0.013977055437862873,"z":0.006036592181771994,"w":0.9374892115592957},"size":15.30586051940918,"orthographic":false}